ratchetapi/__init__.py
ratchetapi/core.py
ratchetapi/exceptions.py
ratchetapi/httpbroker.py
ratchetapi-0.6.dist-info/DESCRIPTION.rst
ratchetapi-0.6.dist-info/METADATA
ratchetapi-0.6.dist-info/metadata.json
ratchetapi-0.6.dist-info/RECORD
ratchetapi-0.6.dist-info/top_level.txt
ratchetapi-0.6.dist-info/WHEEL
