Metadata-Version: 2.0
Name: ratchetapi
Version: 0.6
Summary: Thin wrapper around the SciELO Ratchet RESTful API.
Home-page: http://docs.scielo.org
Author: Fabio Batalha C dos Santos
Author-email: fabio.batalha@scielo.org
License: BSD License
Platform: UNKNOWN
Classifier: Development Status :: 4 - Beta
Classifier: Intended Audience :: Developers
Classifier: Programming Language :: Python
Classifier: Topic :: Software Development :: Libraries :: Python Modules
Requires-Dist: requests (==1.2.3)
